ccloud.py
py_ccloud-0.1.2.dist-info/LICENSE
py_ccloud-0.1.2.dist-info/METADATA
py_ccloud-0.1.2.dist-info/WHEEL
py_ccloud-0.1.2.dist-info/top_level.txt
py_ccloud-0.1.2.dist-info/RECORD
