Metadata-Version: 2.1
Name: py-ccloud
Version: 0.1.2
Summary: Simple Python library wrapping the Confluent Cloud CLI
Home-page: https://github.com/saucelabs/py-ccloud
Author: Pawel Dudzinski
Author-email: pawel.dudzinski@saucelabs.com
License: UNKNOWN
Platform: UNKNOWN
Classifier: Programming Language :: Python :: 3
Classifier: License :: OSI Approved :: MIT License
Classifier: Operating System :: OS Independent
Requires-Dist: executor (==23.2)
